xdtransform/__init__.py
xdtransform/xdtransform.py
xdtransform-0.0.1.data/scripts/xdtransform
xdtransform-0.0.1.dist-info/METADATA
xdtransform-0.0.1.dist-info/WHEEL
xdtransform-0.0.1.dist-info/top_level.txt
xdtransform-0.0.1.dist-info/RECORD
