Metadata-Version: 2.1
Name: xdtransform
Version: 0.0.1
Summary: Library implementing the Microsoft XML Document Transform (XDT) transformation process
Home-page: https://github.com/peshev/python-xdtransform
Author: Peter Peshev
Author-email: peshev@gmail.com
License: UNKNOWN
Platform: UNKNOWN
Classifier: Programming Language :: Python :: 3
Classifier: Operating System :: OS Independent
Requires-Dist: lxml
